odoo/addons/product_analytic_sale/README.rst
odoo/addons/product_analytic_sale/__init__.py
odoo/addons/product_analytic_sale/__manifest__.py
odoo/addons/product_analytic_sale/i18n/eu_ES.po
odoo/addons/product_analytic_sale/i18n/it.po
odoo/addons/product_analytic_sale/i18n/product_analytic_sale.pot
odoo/addons/product_analytic_sale/models/__init__.py
odoo/addons/product_analytic_sale/models/sale_order_line.py
odoo/addons/product_analytic_sale/readme/CONTRIBUTORS.rst
odoo/addons/product_analytic_sale/readme/DESCRIPTION.rst
odoo/addons/product_analytic_sale/static/description/icon.png
odoo/addons/product_analytic_sale/static/description/index.html
odoo/addons/product_analytic_sale/tests/__init__.py
odoo/addons/product_analytic_sale/tests/test_analytic_sale.py
odoo_addon_product_analytic_sale-16.0.1.0.0.5.dist-info/METADATA
odoo_addon_product_analytic_sale-16.0.1.0.0.5.dist-info/WHEEL
odoo_addon_product_analytic_sale-16.0.1.0.0.5.dist-info/top_level.txt
odoo_addon_product_analytic_sale-16.0.1.0.0.5.dist-info/RECORD
